backpack_exchange_sdk/__init__.py
backpack_exchange_sdk/authenticated.py
backpack_exchange_sdk/public.py
backpack_exchange_sdk/py.typed
backpack_exchange_sdk/websocket.py
backpack_exchange_sdk/_base/__init__.py
backpack_exchange_sdk/_base/client.py
backpack_exchange_sdk/_base/errors.py
backpack_exchange_sdk/_base/utils.py
backpack_exchange_sdk/_mixins/__init__.py
backpack_exchange_sdk/_mixins/account.py
backpack_exchange_sdk/_mixins/borrow_lend.py
backpack_exchange_sdk/_mixins/capital.py
backpack_exchange_sdk/_mixins/history.py
backpack_exchange_sdk/_mixins/order.py
backpack_exchange_sdk/_mixins/rfq.py
backpack_exchange_sdk/_mixins/strategy.py
backpack_exchange_sdk/_mixins/public/__init__.py
backpack_exchange_sdk/_mixins/public/assets.py
backpack_exchange_sdk/_mixins/public/borrow_lend_markets.py
backpack_exchange_sdk/_mixins/public/market.py
backpack_exchange_sdk/_mixins/public/prediction.py
backpack_exchange_sdk/_mixins/public/system.py
backpack_exchange_sdk/_mixins/public/trades.py
backpack_exchange_sdk/enums/__init__.py
backpack_exchange_sdk/enums/borrow_lend.py
backpack_exchange_sdk/enums/capital.py
backpack_exchange_sdk/enums/common.py
backpack_exchange_sdk/enums/errors.py
backpack_exchange_sdk/enums/market.py
backpack_exchange_sdk/enums/order.py
backpack_exchange_sdk/enums/position.py
backpack_exchange_sdk/enums/request_enums.py
backpack_exchange_sdk/enums/response_enums.py
backpack_exchange_sdk/enums/rfq.py
backpack_exchange_sdk/enums/strategy.py
backpack_exchange_sdk/enums/system.py
backpack_exchange_sdk-1.1.4.dist-info/licenses/LICENSE
backpack_exchange_sdk-1.1.4.dist-info/METADATA
backpack_exchange_sdk-1.1.4.dist-info/WHEEL
backpack_exchange_sdk-1.1.4.dist-info/top_level.txt
backpack_exchange_sdk-1.1.4.dist-info/RECORD
